nntool/__init__.py
nntool/test_mail.py
nntool/tools.py
nntool/util.py
nntoolQ-0.0.3.dist-info/METADATA
nntoolQ-0.0.3.dist-info/WHEEL
nntoolQ-0.0.3.dist-info/top_level.txt
nntoolQ-0.0.3.dist-info/RECORD
