Metadata-Version: 2.1
Name: nntoolQ
Version: 0.0.3
Summary: nntoolQ
Home-page: http://autozone-prod.pin-dao.cn/
Author: sunny
Author-email: quanningning@pin-dao.cn
License: MIT
Platform: UNKNOWN
Classifier: License :: OSI Approved :: MIT License
Classifier: Programming Language :: Python
Classifier: Programming Language :: Python :: 3
Requires-Python: >=3.8.0
Requires-Dist: yagmail
